README.txt
setup.py
docs/HISTORY.txt
pas/__init__.py
pas.plugins.adpwchange.egg-info/PKG-INFO
pas.plugins.adpwchange.egg-info/SOURCES.txt
pas.plugins.adpwchange.egg-info/dependency_links.txt
pas.plugins.adpwchange.egg-info/entry_points.txt
pas.plugins.adpwchange.egg-info/namespace_packages.txt
pas.plugins.adpwchange.egg-info/not-zip-safe
pas.plugins.adpwchange.egg-info/requires.txt
pas.plugins.adpwchange.egg-info/top_level.txt
pas/plugins/__init__.py
pas/plugins/adpwchange/__init__.py
pas/plugins/adpwchange/configure.zcml
pas/plugins/adpwchange/plugin.py
pas/plugins/adpwchange/templates/addAdPlugin.zpt