Metadata-Version: 1.0
Name: pas.plugins.adpwchange
Version: 1.0
Summary: (Plone)PAS plugin to enable password changes in AD
Home-page: UNKNOWN
Author: Wichert Akkerman
Author-email: wichert@wiggy.net
License: BSD
Keywords: AD PAS PlonePAS Plone
Platform: UNKNOWN
Classifier: Framework :: Zope2
Classifier: Intended Audience :: Developers
Classifier: Intended Audience :: System Administrators
Classifier: License :: OSI Approved :: BSD License
Classifier: License :: OSI Approved :: BSD License
Classifier: Programming Language :: Python
Classifier: Topic :: System :: Systems Administration :: Authentication/Directory
Classifier: Topic :: Software Development :: Libraries :: Python Modules
